MANIFEST.in
README.txt
setup.cfg
setup.py
porter_db/__init__.py
porter_db/porter.py
porter_db.egg-info/PKG-INFO
porter_db.egg-info/SOURCES.txt
porter_db.egg-info/dependency_links.txt
porter_db.egg-info/top_level.txt