Metadata-Version: 1.0
Name: porter-db
Version: 0.0.4
Summary: simple document-based database
Home-page: https://github.com/wrecodde/porter-db
Author: Deji Joseph
Author-email: wrecodde@gmail.com
License: MIT
Platform: UNKNOWN
